xy_wallet/__init__.py
xy_wallet/wallet_main.py
xy_wallet/conf/config.yaml
xy_wallet/conf/abi/abi.json
xy_wallet/conf/keystores/root.keystore
xy_wallet/utils/TokenClass.py
xy_wallet/utils/ToolClass.py
xy_wallet/utils/WalletClass.py
xy_wallet/utils/__init__.py
xy_wallet/utils/BaseAPI/BaseConfig.py
xy_wallet/utils/BaseAPI/BaseEvent.py
xy_wallet/utils/BaseAPI/BaseWallet.py
xy_wallet/utils/BaseAPI/__init__.py
wallet_eth-0.0.2.dist-info/LICENSE
wallet_eth-0.0.2.dist-info/METADATA
wallet_eth-0.0.2.dist-info/WHEEL
wallet_eth-0.0.2.dist-info/entry_points.txt
wallet_eth-0.0.2.dist-info/top_level.txt
wallet_eth-0.0.2.dist-info/RECORD
