Metadata-Version: 2.1
Name: wallet-eth
Version: 0.0.2
Summary: Ethereum wallet
Home-page: https://x1a0.net
Author: xiaoyue
Author-email: xiaoyue2019@outlook.com
Keywords: ethereum,wallet,cryptocurrencies
Requires-Python: >=3.6
License-File: LICENSE
Requires-Dist: click (==8.1.3)
Requires-Dist: eth-account (==0.5.8)
Requires-Dist: PyYAML (==6.0)
Requires-Dist: requests (==2.27.1)
Requires-Dist: setuptools (==49.2.1)
Requires-Dist: web3 (==5.29.2)
